utilpy/__init__.py
utilpy/decorator.py
utilpy/files.py
utilpy/log.py
utilpy/utils.py
utilpy-0.1.4.dist-info/LICENSE
utilpy-0.1.4.dist-info/METADATA
utilpy-0.1.4.dist-info/WHEEL
utilpy-0.1.4.dist-info/top_level.txt
utilpy-0.1.4.dist-info/RECORD
