Metadata-Version: 2.1
Name: utilpy
Version: 0.1.4
Summary: Collection of utils that we use often. 
Home-page: https://github.com/BkrmDahal/utilpy
Author: Bikram Dahal (Arch analytics)
Author-email: bikram@archanalaytics.ai
License: MIT
Platform: UNKNOWN
Classifier: Intended Audience :: Education
Classifier: Intended Audience :: Science/Research
Classifier: Intended Audience :: Developers
Classifier: License :: OSI Approved :: MIT License
Classifier: Operating System :: MacOS :: MacOS X
Classifier: Operating System :: POSIX
Classifier: Operating System :: Unix
Classifier: Programming Language :: Python
Classifier: Programming Language :: Python :: 3
Classifier: Topic :: Scientific/Engineering
Classifier: Topic :: Software Development
Requires-Python: >=3
Requires-Dist: PyYAML
Requires-Dist: requests
Requires-Dist: beautifulsoup4
Requires-Dist: patool
Requires-Dist: loguru
